flywheels/__init__.py
flywheels-0.1.2.dist-info/LICENSE
flywheels-0.1.2.dist-info/METADATA
flywheels-0.1.2.dist-info/WHEEL
flywheels-0.1.2.dist-info/RECORD
